vabot/__init__.py
vabot/base.py
vabot/bot.py
vabot/chatbot.py
vabot/config.py
vabot/debug.py
vabot-0.1.0.dist-info/METADATA
vabot-0.1.0.dist-info/WHEEL
vabot-0.1.0.dist-info/RECORD
